{"updateTime":"2022-12-05 01:56:03","data":[{"full_name":"RomainBeaumontimg2dataset","description":"rom1504","currentPeriodStars":0,"stargazers_count":0,"forks_count":0,"owner":{},"buildBy":[]},{"full_name":"img2dataset","description":"","currentPeriodStars":0,"stargazers_count":0,"forks_count":0,"owner":{},"buildBy":[]},{"full_name":"GeorgeHotztinygrad","description":"geohot","currentPeriodStars":0,"stargazers_count":0,"forks_count":0,"owner":{},"buildBy":[]},{"full_name":"tinygrad","description":"","currentPeriodStars":0,"stargazers_count":0,"forks_count":0,"owner":{},"buildBy":[]},{"full_name":"BryceDrennanimaginAIry","description":"brycedrennan","currentPeriodStars":0,"stargazers_count":0,"forks_count":0,"owner":{},"buildBy":[]},{"full_name":"imaginAIry","description":"","currentPeriodStars":0,"stargazers_count":0,"forks_count":0,"owner":{},"buildBy":[]},{"full_name":"BramGerritsenhomeassistant-powercalc","description":"bramstroker","currentPeriodStars":0,"stargazers_count":0,"forks_count":0,"owner":{},"buildBy":[]},{"full_name":"homeassistant-powercalc","description":"","currentPeriodStars":0,"stargazers_count":0,"forks_count":0,"owner":{},"buildBy":[]},{"full_name":"KenjiMiyakefind-cuda-versions","description":"kenji-miyake","currentPeriodStars":0,"stargazers_count":0,"forks_count":0,"owner":{},"buildBy":[]},{"full_name":"find-cuda-versions","description":"","currentPeriodStars":0,"stargazers_count":0,"forks_count":0,"owner":{},"buildBy":[]},{"full_name":"AzureSDKBotazure-docs-sdk-java","description":"azure-sdk","currentPeriodStars":0,"stargazers_count":0,"forks_count":0,"owner":{},"buildBy":[]},{"full_name":"azure-docs-sdk-java","description":"","currentPeriodStars":0,"stargazers_count":0,"forks_count":0,"owner":{},"buildBy":[]},{"full_name":"JelleZijlstraautotyping","description":"JelleZijlstra","currentPeriodStars":0,"stargazers_count":0,"forks_count":0,"owner":{},"buildBy":[]},{"full_name":"autotyping","description":"","currentPeriodStars":0,"stargazers_count":0,"forks_count":0,"owner":{},"buildBy":[]},{"full_name":"dgtlmoonchangedetection.io","description":"","currentPeriodStars":0,"stargazers_count":0,"forks_count":0,"owner":{},"buildBy":[]},{"full_name":"changedetection.io","description":"","currentPeriodStars":0,"stargazers_count":0,"forks_count":0,"owner":{},"buildBy":[]},{"full_name":"BasNijholtadaptive-lighting","description":"basnijholt","currentPeriodStars":0,"stargazers_count":0,"forks_count":0,"owner":{},"buildBy":[]},{"full_name":"adaptive-lighting","description":"","currentPeriodStars":0,"stargazers_count":0,"forks_count":0,"owner":{},"buildBy":[]},{"full_name":"/rootzollraspiblitz","description":"rootzoll","currentPeriodStars":0,"stargazers_count":0,"forks_count":0,"owner":{},"buildBy":[]},{"full_name":"raspiblitz","description":"","currentPeriodStars":0,"stargazers_count":0,"forks_count":0,"owner":{},"buildBy":[]},{"full_name":"AlexRogozhnikoveinops","description":"arogozhnikov","currentPeriodStars":0,"stargazers_count":0,"forks_count":0,"owner":{},"buildBy":[]},{"full_name":"einops","description":"","currentPeriodStars":0,"stargazers_count":0,"forks_count":0,"owner":{},"buildBy":[]},{"full_name":"AlexGrönholmapscheduler","description":"agronholm","currentPeriodStars":0,"stargazers_count":0,"forks_count":0,"owner":{},"buildBy":[]},{"full_name":"apscheduler","description":"","currentPeriodStars":0,"stargazers_count":0,"forks_count":0,"owner":{},"buildBy":[]},{"full_name":"CarltonGibsondjango-filter","description":"carltongibson","currentPeriodStars":0,"stargazers_count":0,"forks_count":0,"owner":{},"buildBy":[]},{"full_name":"django-filter","description":"","currentPeriodStars":0,"stargazers_count":0,"forks_count":0,"owner":{},"buildBy":[]},{"full_name":"WangchongZhouxeHentai","description":"fffonion","currentPeriodStars":0,"stargazers_count":0,"forks_count":0,"owner":{},"buildBy":[]},{"full_name":"xeHentai","description":"","currentPeriodStars":0,"stargazers_count":0,"forks_count":0,"owner":{},"buildBy":[]},{"full_name":"MuLiautocut","description":"mli","currentPeriodStars":0,"stargazers_count":0,"forks_count":0,"owner":{},"buildBy":[]},{"full_name":"autocut","description":"","currentPeriodStars":0,"stargazers_count":0,"forks_count":0,"owner":{},"buildBy":[]},{"full_name":"RossWightmanpytorch-image-models","description":"rwightman","currentPeriodStars":0,"stargazers_count":0,"forks_count":0,"owner":{},"buildBy":[]},{"full_name":"pytorch-image-models","description":"","currentPeriodStars":0,"stargazers_count":0,"forks_count":0,"owner":{},"buildBy":[]},{"full_name":"FrédéricCollonvaljupyter-project","description":"fcollonval","currentPeriodStars":0,"stargazers_count":0,"forks_count":0,"owner":{},"buildBy":[]},{"full_name":"jupyter-project","description":"","currentPeriodStars":0,"stargazers_count":0,"forks_count":0,"owner":{},"buildBy":[]},{"full_name":"KentaroWadalabelme","description":"wkentaro","currentPeriodStars":0,"stargazers_count":0,"forks_count":0,"owner":{},"buildBy":[]},{"full_name":"labelme","description":"","currentPeriodStars":0,"stargazers_count":0,"forks_count":0,"owner":{},"buildBy":[]},{"full_name":"CostaHuangcleanrl","description":"vwxyzjn","currentPeriodStars":0,"stargazers_count":0,"forks_count":0,"owner":{},"buildBy":[]},{"full_name":"cleanrl","description":"","currentPeriodStars":0,"stargazers_count":0,"forks_count":0,"owner":{},"buildBy":[]},{"full_name":"MinJaeKwondiagrams","description":"mingrammer","currentPeriodStars":0,"stargazers_count":0,"forks_count":0,"owner":{},"buildBy":[]},{"full_name":"diagrams","description":"","currentPeriodStars":0,"stargazers_count":0,"forks_count":0,"owner":{},"buildBy":[]},{"full_name":"Charles-AxelDeinprofessional-programming","description":"charlax","currentPeriodStars":0,"stargazers_count":0,"forks_count":0,"owner":{},"buildBy":[]},{"full_name":"professional-programming","description":"","currentPeriodStars":0,"stargazers_count":0,"forks_count":0,"owner":{},"buildBy":[]},{"full_name":"RangiLyunanodet","description":"","currentPeriodStars":0,"stargazers_count":0,"forks_count":0,"owner":{},"buildBy":[]},{"full_name":"nanodet","description":"","currentPeriodStars":0,"stargazers_count":0,"forks_count":0,"owner":{},"buildBy":[]},{"full_name":"ZaidaZhouminitorch","description":"zhouzaida","currentPeriodStars":0,"stargazers_count":0,"forks_count":0,"owner":{},"buildBy":[]},{"full_name":"minitorch","description":"","currentPeriodStars":0,"stargazers_count":0,"forks_count":0,"owner":{},"buildBy":[]},{"full_name":"vn.pyvnpy","description":"vnpy","currentPeriodStars":0,"stargazers_count":0,"forks_count":0,"owner":{},"buildBy":[]},{"full_name":"vnpy","description":"","currentPeriodStars":0,"stargazers_count":0,"forks_count":0,"owner":{},"buildBy":[]},{"full_name":"FlorianRothLoki","description":"Neo23x0","currentPeriodStars":0,"stargazers_count":0,"forks_count":0,"owner":{},"buildBy":[]},{"full_name":"Loki","description":"","currentPeriodStars":0,"stargazers_count":0,"forks_count":0,"owner":{},"buildBy":[]}]}